mttools/AlgebraTools/__init__.py
mttools/CalculusTools/__init__.py
mttools/Constants.py
mttools/Core.py
mttools/FunctionTools.py
mttools/__init__.py
mttools/geometry_tools/__init__.py
mttools/linear_algebra_tools/__init__.py
mttools/linear_algebra_tools/matrix.py
mttools/linear_algebra_tools/vector.py
mttools/number_theory_tools/Primes.py
mttools/number_theory_tools/__init__.py
mttools/utils/__init__.py
mttools/utils/exceptions.py
mttools/utils/profilers.py
mttools/utils/types.py
mttools-0.2.3.dist-info/LICENSE
mttools-0.2.3.dist-info/WHEEL
mttools-0.2.3.dist-info/METADATA
mttools-0.2.3.dist-info/RECORD
